LMC_Winds/__init__.py
LMC_Winds/def_norm_guesses.py
LMC_Winds/def_normalize.py
LMC_Winds/def_read_STSCI.py
LMC_Winds/def_read_line_transitions.py
LMC_Winds/def_velocity_conversions.py
LMC_Winds/example.py
LMC_Winds/fitting.py
LMC_Winds/whichLSF.py
LMC_Winds-0.0.5.dist-info/LICENSE.txt
LMC_Winds-0.0.5.dist-info/METADATA
LMC_Winds-0.0.5.dist-info/WHEEL
LMC_Winds-0.0.5.dist-info/top_level.txt
LMC_Winds-0.0.5.dist-info/RECORD
