Metadata-Version: 2.1
Name: LMC-Winds
Version: 0.0.5
Summary: Python package for analyzing HST data related to LMC
Author: TCU Students
Author-email: suraj.poudel@tcu.edu
License: None
License-File: LICENSE.txt
